atdict/__init__.py
atdict/_version.py
atdict/obj.py
atdict-0.9.4.dist-info/LICENSE
atdict-0.9.4.dist-info/METADATA
atdict-0.9.4.dist-info/WHEEL
atdict-0.9.4.dist-info/top_level.txt
atdict-0.9.4.dist-info/RECORD
