Metadata-Version: 2.1
Name: atdict
Version: 0.9.4
Summary: Attribute-access ordered dictionary
Home-page: https://github.com/alphatwirl/atdict
Author: Tai Sakuma
Author-email: tai.sakuma@gmail.com
License: UNKNOWN
Platform: UNKNOWN
Classifier: Development Status :: 4 - Beta
Classifier: Intended Audience :: Developers
Classifier: Intended Audience :: End Users/Desktop
Classifier: License :: OSI Approved :: BSD License
Classifier: Programming Language :: Python :: 3.6
Classifier: Programming Language :: Python :: 3.7
Classifier: Programming Language :: Python :: 3.8
Classifier: Programming Language :: Python :: 3.9
Provides-Extra: tests
Requires-Dist: pytest (>=6.2) ; extra == 'tests'
Requires-Dist: pytest-cov (>=2.11) ; extra == 'tests'
